intake_esgf/__init__.py
intake_esgf/_version.py
intake_esgf/base.py
intake_esgf/catalog.py
intake_esgf/config.py
intake_esgf/database.py
intake_esgf/exceptions.py
intake_esgf/logging.py
intake_esgf/projects.py
intake_esgf/py.typed
intake_esgf/core/__init__.py
intake_esgf/core/globus.py
intake_esgf/core/solr.py
intake_esgf/core/stac.py
intake_esgf/tests/__init__.py
intake_esgf/tests/conftest.py
intake_esgf/tests/test_base.py
intake_esgf/tests/test_catalog.py
intake_esgf/tests/test_config.py
intake_esgf/tests/test_database.py
intake_esgf/tests/test_exceptions.py
intake_esgf/tests/test_init.py
intake_esgf/tests/test_logging.py
intake_esgf/tests/core/test_globus.py
intake_esgf/tests/core/test_init.py
intake_esgf/tests/core/test_solr.py
intake_esgf/tests/core/test_stac.py
intake_esgf/tests/project/test_DRCDP.py
intake_esgf/tests/project/test_WrPMIP.py
intake_esgf/tests/project/test_cmip3.py
intake_esgf/tests/project/test_cmip5.py
intake_esgf/tests/project/test_cmip6.py
intake_esgf/tests/project/test_cmip6plus.py
intake_esgf/tests/project/test_input4MIPs.py
intake_esgf/tests/project/test_obs4MIPs.py
intake_esgf-2026.1.26.dist-info/licenses/LICENSE
intake_esgf-2026.1.26.dist-info/METADATA
intake_esgf-2026.1.26.dist-info/WHEEL
intake_esgf-2026.1.26.dist-info/top_level.txt
intake_esgf-2026.1.26.dist-info/RECORD
