Metadata-Version: 2.4
Name: intake-esgf
Version: 2026.1.26
Summary: Programmatic access to the ESGF holdings
Author-email: Nathan Collier <nathaniel.collier@gmail.com>
License: Copyright 2024 onwards Earth System Grid Federation 2 - US
Classifier: Development Status :: 4 - Beta
Classifier: License :: OSI Approved :: BSD License
Classifier: Operating System :: OS Independent
Classifier: Programming Language :: Python :: 3
Classifier: Programming Language :: Python :: 3.12
Classifier: Programming Language :: Python :: 3.13
Classifier: Programming Language :: Python :: 3.14
Classifier: Intended Audience :: Science/Research
Classifier: Topic :: Scientific/Engineering
Requires-Python: >=3.12
License-File: LICENSE
Requires-Dist: dask>=2024.12.0
Requires-Dist: globus-sdk<4.0.0
Requires-Dist: netcdf4>=1.7.2
Requires-Dist: pandas>=2.2.3
Requires-Dist: pystac-client>=0.8.6
Requires-Dist: pyyaml>=6.0.2
Requires-Dist: requests>=2.32.3
Requires-Dist: requests-cache>=1.2.1
Requires-Dist: tqdm>=4.67.1
Requires-Dist: xarray>=2024.11.0
Dynamic: license-file
